glom/__init__.py
glom/__main__.py
glom/_version.py
glom/chainmap_backport.py
glom/cli.py
glom/core.py
glom/grouping.py
glom/matching.py
glom/mutation.py
glom/reduction.py
glom/reprlib_backport.py
glom/streaming.py
glom/tutorial.py
glom/test/__init__.py
glom/test/conftest.py
glom/test/perf_report.py
glom/test/test_basic.py
glom/test/test_check.py
glom/test/test_cli.py
glom/test/test_error.py
glom/test/test_fill.py
glom/test/test_grouping.py
glom/test/test_match.py
glom/test/test_mutation.py
glom/test/test_path_and_t.py
glom/test/test_reduction.py
glom/test/test_scope_vars.py
glom/test/test_snippets.py
glom/test/test_spec.py
glom/test/test_streaming.py
glom/test/test_target_types.py
glom/test/test_tutorial.py
glom/test/data/test_invalid.toml
glom/test/data/test_invalid.yaml
glom/test/data/test_valid.toml
glom/test/data/test_valid.yaml
glom-25.12.0.dist-info/LICENSE
glom-25.12.0.dist-info/METADATA
glom-25.12.0.dist-info/WHEEL
glom-25.12.0.dist-info/entry_points.txt
glom-25.12.0.dist-info/top_level.txt
glom-25.12.0.dist-info/RECORD
