Metadata-Version: 2.1
Name: glom
Version: 25.12.0
Summary: A declarative object transformer and formatter, for conglomerating nested data.
Home-page: https://github.com/mahmoud/glom
Author: Mahmoud Hashemi and Kurt Rose
Author-email: mahmoud@hatnote.com
License: UNKNOWN
Project-URL: Documentation, https://glom.readthedocs.io/en/latest/
Platform: any
Classifier: Topic :: Utilities
Classifier: Intended Audience :: Developers
Classifier: Topic :: Software Development :: Libraries
Classifier: Development Status :: 5 - Production/Stable
Classifier: Programming Language :: Python :: 3.7
Classifier: Programming Language :: Python :: 3.8
Classifier: Programming Language :: Python :: 3.9
Classifier: Programming Language :: Python :: 3.10
Classifier: Programming Language :: Python :: 3.11
Classifier: Programming Language :: Python :: 3.12
Classifier: Programming Language :: Python :: 3.13
Classifier: Programming Language :: Python :: 3.14
Classifier: Programming Language :: Python :: Implementation :: CPython
Classifier: Programming Language :: Python :: Implementation :: PyPy
Classifier: License :: OSI Approved :: BSD License
Provides-Extra: toml
Provides-Extra: yaml
